[{"start_year":2005,"count":338},{"start_year":2006,"count":424},{"start_year":2007,"count":442},{"start_year":2008,"count":430},{"start_year":2009,"count":571},{"start_year":2010,"count":543},{"start_year":2011,"count":475},{"start_year":2012,"count":442},{"start_year":2013,"count":459},{"start_year":2014,"count":451},{"start_year":2015,"count":498},{"start_year":2016,"count":471},{"start_year":2017,"count":495},{"start_year":2018,"count":520},{"start_year":2019,"count":464},{"start_year":2020,"count":871},{"start_year":2021,"count":1180},{"start_year":2022,"count":852},{"start_year":2023,"count":638},{"start_year":2024,"count":429}]